dockermysqlexample.py
dockermysqlexample-0.0.4.dist-info/LICENSE.txt
dockermysqlexample-0.0.4.dist-info/METADATA
dockermysqlexample-0.0.4.dist-info/WHEEL
dockermysqlexample-0.0.4.dist-info/RECORD
