Metadata-Version: 2.3
Name: DockerMySqlExample
Version: 0.0.4
Summary: Template for new Python projects.
License: MIT
Author: Hendrik du Toit
Author-email: hendrik@brightedge.co.za
Maintainer: Hendrik du Toit
Maintainer-email: hendrikdt@citiqprepaid.co.za
Requires-Python: >=3.10
Classifier: Development Status :: 3 - Alpha
Classifier: Intended Audience :: Developers
Classifier: Intended Audience :: Information Technology
Classifier: Intended Audience :: System Administrators
Classifier: License :: OSI Approved :: MIT License
Classifier: Topic :: Software Development :: Libraries :: Python Modules
Classifier: Topic :: System :: Archiving :: Packaging
Classifier: Programming Language :: Python :: 3.10
Classifier: Programming Language :: Python :: 3.11
Classifier: Programming Language :: Python :: 3.12
Classifier: Programming Language :: Python :: 3.13
Requires-Dist: fastapi (>=0.115.11,<0.116.0)
Requires-Dist: pymysql (>=1.1.1,<2.0.0)
Requires-Dist: uvicorn (>=0.34.0,<0.35.0)
Project-URL: Changelog, https://github.com/hendrikdutoit/DockerMySqlExample/blob/enhancement/master/ReleaseNotes.md
Project-URL: Homepage, https://github.com/hendrikdutoit/DockerMySqlExample
Project-URL: Issues, https://github.com/hendrikdutoit/DockerMySqlExample/issues
Project-URL: Repository, https://github.com/hendrikdutoit/DockerMySqlExample.git
